sierra/__cli__.py
sierra/__init__.py
sierra/_version.py
sierra/conf/__init__.py
sierra/conf/about/sierra.yaml
sierra/conf/fetcher/sierraclub.yaml
sierra/fetcher/__init__.py
sierra/fetcher/sierra.py
sierra/py.typed
sierraclub-0.2.0.dist-info/LICENSE
sierraclub-0.2.0.dist-info/METADATA
sierraclub-0.2.0.dist-info/WHEEL
sierraclub-0.2.0.dist-info/entry_points.txt
sierraclub-0.2.0.dist-info/RECORD
